zypper_patch_status_collector/__init__.py
zypper_patch_status_collector/__main__.py
zypper_patch_status_collector/_cli.py
zypper_patch_status_collector/_model.py
zypper_patch_status_collector/_prometheus.py
zypper_patch_status_collector/_zypper.py
zypper_patch_status_collector-0.3.1.dist-info/LICENSE.txt
zypper_patch_status_collector-0.3.1.dist-info/METADATA
zypper_patch_status_collector-0.3.1.dist-info/WHEEL
zypper_patch_status_collector-0.3.1.dist-info/entry_points.txt
zypper_patch_status_collector-0.3.1.dist-info/top_level.txt
zypper_patch_status_collector-0.3.1.dist-info/RECORD
