Metadata-Version: 2.1
Name: zypper-patch-status-collector
Version: 0.3.1
Summary: Exports patch status in Prometheus-compatible format.
Home-page: https://gitlab.com/Marix/zypper-patch-status-collector
Author: Matthias Bach
Author-email: marix@marix.org
License: GPL-3.0+
Platform: UNKNOWN
Classifier: Development Status :: 4 - Beta
Classifier: Environment :: Console
Classifier: Intended Audience :: System Administrators
Classifier: License :: OSI Approved :: GNU General Public License v3 or later (GPLv3+)
Classifier: Operating System :: POSIX :: Linux
Classifier: Programming Language :: Python :: 3
Classifier: Programming Language :: Python :: 3.6
Classifier: Programming Language :: Python :: 3.8
Classifier: Topic :: System :: Monitoring
Classifier: Topic :: Utilities
Requires-Dist: setuptools
